minivc/__init__.py
minivc/cli.py
minivc/core.py
minivc/ignore.py
minivc-0.2.0.dist-info/METADATA
minivc-0.2.0.dist-info/WHEEL
minivc-0.2.0.dist-info/entry_points.txt
minivc-0.2.0.dist-info/top_level.txt
minivc-0.2.0.dist-info/RECORD
